scrapy_cffi/__init__.py
scrapy_cffi/crawler.py
scrapy_cffi/settings.py
scrapy_cffi/commands/__init__.py
scrapy_cffi/commands/base.py
scrapy_cffi/commands/demo.py
scrapy_cffi/commands/genspider.py
scrapy_cffi/commands/main.py
scrapy_cffi/commands/startproject.py
scrapy_cffi/core/__init__.py
scrapy_cffi/core/api.py
scrapy_cffi/core/engine.py
scrapy_cffi/core/sessions.py
scrapy_cffi/core/tasks.py
scrapy_cffi/core/downloader/__init__.py
scrapy_cffi/core/downloader/fetch.py
scrapy_cffi/core/downloader/selector.py
scrapy_cffi/core/downloader/internet/__init__.py
scrapy_cffi/core/downloader/internet/registry.py
scrapy_cffi/core/downloader/internet/request.py
scrapy_cffi/core/downloader/internet/response.py
scrapy_cffi/core/scheduler/__init__.py
scrapy_cffi/core/scheduler/api.py
scrapy_cffi/core/scheduler/base.py
scrapy_cffi/core/scheduler/rabbitmq.py
scrapy_cffi/core/scheduler/redis.py
scrapy_cffi/cpy/__init__.py
scrapy_cffi/cpy/loader.py
scrapy_cffi/cpy/cpy_resources/bloom/bloom.pyi
scrapy_cffi/cpy/cpy_resources/bloom/fallback.py
scrapy_cffi/cpy/cpy_resources/bloom/wrapper.py
scrapy_cffi/databases/__init__.py
scrapy_cffi/databases/mongodb.py
scrapy_cffi/databases/mysql.py
scrapy_cffi/databases/redis.py
scrapy_cffi/dupefilter/__init__.py
scrapy_cffi/dupefilter/api.py
scrapy_cffi/dupefilter/base.py
scrapy_cffi/dupefilter/redis.py
scrapy_cffi/exceptions/__init__.py
scrapy_cffi/exceptions/base.py
scrapy_cffi/extensions/__init__.py
scrapy_cffi/extensions/base.py
scrapy_cffi/extensions/signal_manager.py
scrapy_cffi/extensions/signals.py
scrapy_cffi/extensions/singal_info.py
scrapy_cffi/extensions/statistics.py
scrapy_cffi/hooks/__init__.py
scrapy_cffi/hooks/base.py
scrapy_cffi/hooks/interceptors.py
scrapy_cffi/hooks/pipelines.py
scrapy_cffi/hooks/signals.py
scrapy_cffi/hooks/spiders.py
scrapy_cffi/interceptors/__init__.py
scrapy_cffi/interceptors/api.py
scrapy_cffi/interceptors/base.py
scrapy_cffi/interceptors/chains.py
scrapy_cffi/interceptors/spiders.py
scrapy_cffi-0.2.4.dist-info/licenses/LICENSE
scrapy_cffi-0.2.4.dist-info/METADATA
scrapy_cffi-0.2.4.dist-info/WHEEL
scrapy_cffi-0.2.4.dist-info/entry_points.txt
scrapy_cffi-0.2.4.dist-info/top_level.txt
scrapy_cffi-0.2.4.dist-info/RECORD
