Metadata-Version: 2.4
Name: scrapy_cffi
Version: 0.2.4
Summary: An asyncio-style web scraping framework inspired by Scrapy, powered by curl_cffi.
Author: aFunnyStrange
License-Expression: BSD-3-Clause
Project-URL: Homepage, https://github.com/aFunnyStrange/scrapy_cffi
Requires-Python: >=3.7
License-File: LICENSE
Requires-Dist: curl_cffi
Requires-Dist: PyExecjs
Requires-Dist: orjson
Requires-Dist: json5
Requires-Dist: toml
Requires-Dist: pydantic>=2.0.0
Requires-Dist: jinja2
Requires-Dist: tenacity
Requires-Dist: redis>=5.0.0
Requires-Dist: parsel
Requires-Dist: regex
Requires-Dist: dotenv
Provides-Extra: windows
Requires-Dist: python-magic-bin; extra == "windows"
Provides-Extra: unix
Requires-Dist: python-magic; extra == "unix"
Dynamic: license-file
